Metadata-Version: 2.1
Name: distributions-nf
Version: 0.1
Summary: Gaussian distributions
